{
  "lists": [
    {
      "id": 1,
      "title": "Mercado"
    },
    {
      "id": 2,
      "title": "Trabalho"
    },
    {
      "title": "Hammerfall",
      "id": 3
    },
    {
      "title": "josue",
      "id": 4
    },
    {
      "title": "mouse card",
      "id": 5
    }
  ],
  "tasks": [
    {
      "listId": 2,
      "title": "Organização das tarefas",
      "id": 4,
      "isChecked": false
    },
    {
      "listId": 1,
      "title": "Comprar legumes",
      "isChecked": false,
      "id": 6
    },
    {
      "id": 12
    },
    {
      "id": 13
    },
    {
      "listId": 2,
      "title": "tomilho",
      "isChecked": false,
      "id": 27
    },
    {
      "listId": 1,
      "title": "asdasd",
      "isChecked": false,
      "id": 36
    },
    {
      "listId": 1,
      "title": "asdasd",
      "isChecked": false,
      "id": 37
    },
    {
      "listId": 1,
      "title": "asdrubal",
      "isChecked": false,
      "id": 38
    },
    {
      "listId": 1,
      "title": "hortovaldo",
      "isChecked": false,
      "id": 39
    },
    {
      "listId": 3,
      "title": "asdasdasd 12111111111111111",
      "isChecked": false,
      "id": 40
    },
    {
      "listId": 4,
      "title": "aaaaaaaaaaaaaaaaaaaaaaaaaaaaaaaaaaaaaaaaaaaaaa",
      "isChecked": false,
      "id": 41
    }
  ]
}